talkflow/__init__.py
talkflow/cli.py
talkflow/talkflow.py
talkflow-0.1.0.dist-info/AUTHORS.rst
talkflow-0.1.0.dist-info/LICENSE
talkflow-0.1.0.dist-info/METADATA
talkflow-0.1.0.dist-info/WHEEL
talkflow-0.1.0.dist-info/entry_points.txt
talkflow-0.1.0.dist-info/top_level.txt
talkflow-0.1.0.dist-info/RECORD
