Metadata-Version: 2.1
Name: talkflow
Version: 0.1.0
Summary: Full function pplatform for conversational agent
Home-page: https://github.com/howl-anderson/talkflow
Author: Xiaoquan Kong
Author-email: u1mail2me@gmail.com
License: MIT license
Keywords: talkflow
Platform: UNKNOWN
Classifier: Development Status :: 2 - Pre-Alpha
Classifier: Intended Audience :: Developers
Classifier: License :: OSI Approved :: MIT License
Classifier: Natural Language :: English
Classifier: Programming Language :: Python :: 3
Classifier: Programming Language :: Python :: 3.5
Classifier: Programming Language :: Python :: 3.6
Classifier: Programming Language :: Python :: 3.7
Classifier: Programming Language :: Python :: 3.8
Requires-Python: >=3.5
Requires-Dist: Click (>=7.0)
